[
    {
        "id": 1,
        "first_name": "Kenneth",
        "last_name": "Kang",
        "email": "ken@gmail.com",
        "phone": "2139128098"
    },
    {
        "id": 2,
        "first_name": "Navid",
        "last_name": "Shaghaghi",
        "email": "navid@example.com",
        "phone": "555-1234"
    },
    {
        "id": 3,
        "first_name": "Sarah",
        "last_name": "Lee",
        "email": "sarah@example.com",
        "phone": "555-9876"
    },
    {
        "id": 6,
        "first_name": "Kenneth",
        "last_name": "Kang",
        "email": "kennethkang0715@gmail.com",
        "phone": "6693092180"
    },
    {
        "id": 4,
        "first_name": "diofsods",
        "last_name": "dfjdj",
        "email": "ccjdoijo@gmail.com",
        "phone": "123456789"
    },
    {
        "id": 5,
        "first_name": "Conner",
        "last_name": "Chen",
        "email": "cchen19@scu.edu",
        "phone": "6695889088"
    }
]