[
    {
        "id": 1,
        "first_name": "Kenneth",
        "last_name": "Kang",
        "email": "ken@gmail.com",
        "phone": "2139128098"
    },
    {
        "id": 2,
        "first_name": "Navid",
        "last_name": "Shaghaghi",
        "email": "navid@example.com",
        "phone": "555-1234"
    },
    {
        "id": 3,
        "first_name": "Sarah",
        "last_name": "Lee",
        "email": "sarah@example.com",
        "phone": "555-9876"
    },
    {
        "id": 4,
        "first_name": "Kenneth",
        "last_name": "Kang",
        "email": "kennethkang0715@gmail.com",
        "phone": "6693092180"
    }
]